{
    "sourceFile": "assets/language/ar.json",
    "activeCommit": 0,
    "commits": [
        {
            "activePatchIndex": 10,
            "patches": [
                {
                    "date": 1695393771288,
                    "content": "Index: \n===================================================================\n--- \n+++ \n"
                },
                {
                    "date": 1695393799577,
                    "content": "Index: \n===================================================================\n--- \n+++ \n@@ -80,13 +80,13 @@\n \"Please enter your name\":\"ادخل اسمك رجاء\",\r\n \"Enter your name\":\"ادخل اسمك\",\r\n \"Please enter email or username\":\"ادخل البريدالاكتروني رجاء\",\r\n \"Enter email or username\":\"ادخل البريد الاكتروني\",\r\n-\"Please enter a password\":\"ادخل كلمة السر رجاء\",\r\n+\"Please enter a password\":\"ادخل كلمة المرور رجاء\",\r\n \"Password\":\"كلمة المرور\",\r\n-\"Please confirm your password\":\"قم باعادة كتابة كلمة السر رجاء \",\r\n-\"Passwords do not match\":\"كلمات السر غير متشابهة\",\r\n-\"Confirm Password\":\"التحقق من كلمة السر\",\r\n+\"Please confirm your password\":\"قم باعادة كتابة كلمة المرور رجاء \",\r\n+\"Passwords do not match\":\"كلمات المرور غير متشابهة\",\r\n+\"Confirm Password\":\"التحقق من كلمة المرور\",\r\n \"----------- OR -----------\":\"----------- او -----------\",\r\n \"Entry is restricted\":\"الدخول مقيد\",\r\n \"Please check with the admin to obtain access permission\":\"الرجاء مراجعة الادمن حتى يعطيك صلاحية الدخول \",\r\n \"OK\":\"حسنا\",\r\n"
                },
                {
                    "date": 1695393812870,
                    "content": "Index: \n===================================================================\n--- \n+++ \n@@ -85,9 +85,9 @@\n \"Password\":\"كلمة المرور\",\r\n \"Please confirm your password\":\"قم باعادة كتابة كلمة المرور رجاء \",\r\n \"Passwords do not match\":\"كلمات المرور غير متشابهة\",\r\n \"Confirm Password\":\"التحقق من كلمة المرور\",\r\n-\"----------- OR -----------\":\"----------- او -----------\",\r\n+\"----------- OR -----------\":\"----------- أو -----------\",\r\n \"Entry is restricted\":\"الدخول مقيد\",\r\n \"Please check with the admin to obtain access permission\":\"الرجاء مراجعة الادمن حتى يعطيك صلاحية الدخول \",\r\n \"OK\":\"حسنا\",\r\n \"No data available.\":\"لا يوجد بيانات متاحة.\",\r\n"
                },
                {
                    "date": 1695393833914,
                    "content": "Index: \n===================================================================\n--- \n+++ \n@@ -78,9 +78,9 @@\n \"Nov\":\"نوفمبر \",\r\n \"Dec\":\"ديسمبر \",\r\n \"Please enter your name\":\"ادخل اسمك رجاء\",\r\n \"Enter your name\":\"ادخل اسمك\",\r\n-\"Please enter email or username\":\"ادخل البريدالاكتروني رجاء\",\r\n+\"Please enter email or username\":\"ادخل البريدالالكتروني رجاء\",\r\n \"Enter email or username\":\"ادخل البريد الاكتروني\",\r\n \"Please enter a password\":\"ادخل كلمة المرور رجاء\",\r\n \"Password\":\"كلمة المرور\",\r\n \"Please confirm your password\":\"قم باعادة كتابة كلمة المرور رجاء \",\r\n"
                },
                {
                    "date": 1695393847605,
                    "content": "Index: \n===================================================================\n--- \n+++ \n@@ -79,9 +79,9 @@\n \"Dec\":\"ديسمبر \",\r\n \"Please enter your name\":\"ادخل اسمك رجاء\",\r\n \"Enter your name\":\"ادخل اسمك\",\r\n \"Please enter email or username\":\"ادخل البريدالالكتروني رجاء\",\r\n-\"Enter email or username\":\"ادخل البريد الاكتروني\",\r\n+\"Enter email or username\":\"ادخل البريد الالكتروني\",\r\n \"Please enter a password\":\"ادخل كلمة المرور رجاء\",\r\n \"Password\":\"كلمة المرور\",\r\n \"Please confirm your password\":\"قم باعادة كتابة كلمة المرور رجاء \",\r\n \"Passwords do not match\":\"كلمات المرور غير متشابهة\",\r\n"
                },
                {
                    "date": 1695393861553,
                    "content": "Index: \n===================================================================\n--- \n+++ \n@@ -87,9 +87,9 @@\n \"Passwords do not match\":\"كلمات المرور غير متشابهة\",\r\n \"Confirm Password\":\"التحقق من كلمة المرور\",\r\n \"----------- OR -----------\":\"----------- أو -----------\",\r\n \"Entry is restricted\":\"الدخول مقيد\",\r\n-\"Please check with the admin to obtain access permission\":\"الرجاء مراجعة الادمن حتى يعطيك صلاحية الدخول \",\r\n+\"Please check with the admin to obtain access permission\":\"الرجاء مراجعة الادمن للحصول يعطيك صلاحية الدخول \",\r\n \"OK\":\"حسنا\",\r\n \"No data available.\":\"لا يوجد بيانات متاحة.\",\r\n \"Change User Rloe\":\"تغير دور المستخدم\",\r\n \"Delete User\":\"حذف المستخدم\",\r\n"
                },
                {
                    "date": 1695393871027,
                    "content": "Index: \n===================================================================\n--- \n+++ \n@@ -0,0 +1,112 @@\n+{\r\n+\"Inbox\":\"الوارد\",\r\n+\"Pending\" :\"معلقة\",\r\n+\"In Progress\":\"جاري المعالجة\",\r\n+\"Completed\":\"مكتمل\",\r\n+\"New Inbox\":\" بريد جديد \",\r\n+\"Home Page\":\" الصفحة الرئيسية\",\r\n+\"Profile Page\" :\"الصفحة الشخصية\",\r\n+\"Senders\" :\"المرسلين\",\r\n+\"User Management\":\"إدارةالمستخدم\",\r\n+\"Terms Of Service\":\"شروط الخدمة\",\r\n+\"Usage Policy\":\"سياسة الاستخدام\",\r\n+\"Search\":\"بحث\",\r\n+\"Login\":\"تسجيل الدخول\",\r\n+\"Sign up\":\"انشاء حساب\",\r\n+\"Foreign\":\"مؤسسات اجنبية\",\r\n+  \"Official Organiztions\":\"مؤسسات حكومية \",\r\n+  \"Official Organizations\":\"مؤسسات حكومية \",\r\n+  \"NGOs\":\"مؤسسات مجتمع المدني \",\r\n+  \"Others\":\"غيرها\",\r\n+  \"Other\":\"غيرها\",\r\n+  \"Tags\":\"علامات\",\r\n+  \"Language\":\"اللغة\",\r\n+  \"Logout\":\"تسجيل الخروج\",\r\n+  \"Edit Profile\":\"تعديل الملف الشخصي \",\r\n+  \"Name:\":\"الاسم:\",\r\n+  \"UPDATE PROFILE\":\"تحديث  الملف الشخصي\",\r\n+  \"Email:\":\"ايميل:\",\r\n+  \"Role:\":\"الدور:\",\r\n+  \"Cancel\":\"الغاء\",\r\n+  \"Filter\":\"فلترة\",\r\n+  \"Done\":\"تاكيد\",\r\n+  \"Clear\":\"مسح الاختيار\",\r\n+  \"Start Date\":\"تاريخ البدء\",\r\n+  \"End Date\":\"تاريخ الانتهاء\",\r\n+  \"Sellect Your Date\":\"اختار التاريخ المناسب\",\r\n+  \"Search ...\":\"بحث ...\",\r\n+  \"All Tags\":\"كل العلامات\",\r\n+  \"Sender\":\"المرسل\",\r\n+  \"Please enter a sender name\":\"ادخل اسم المرسل رجاء\",\r\n+  \"Mail Created Successfully\":\"تم انشائ الايميل بنجاح\",\r\n+  \"Please enter a mobile number\":\"ادخل رقم الهاتف رجاء\",\r\n+  \"Mobile\":\"الهاتف\",\r\n+  \"Category\":\"الفئة\",\r\n+  \"Please enter a title of mail\":\"ادخل عنوان الايميل رجاء\",\r\n+  \"Title of mail\":\"عنوان الايميل\",\r\n+  \"Description\":\"الوصف\",\r\n+  \"Please enter an archive number\":\"ادخل رقم الارشيف رجاء\",\r\n+  \"Archive number\":\"رقم الارشيف\",\r\n+  \"Add Decsision ...\":\"ادخل القرار ...\",\r\n+  \"Add image\":\"اضف صورة\",\r\n+  \"Descision\":\"القرار\",\r\n+  \"Add new activity ...\":\"اضف نشاط جديد ...\",\r\n+  \"Activity\":\"النشاط\",\r\n+  \"Mail Details\":\"تفاصيل الايميل\",\r\n+\"Mail Updated Successfully\":\"تم تحديث الايميل بنجاح\",\r\n+\"Status\":\"الحالة\",\r\n+\"Add status\":\"اضافة حالة\",\r\n+\"Add new tag ...\":\"اضافة علامة ...\",\r\n+\"Date\":\"التاريخ\",\r\n+\"Mon\":\"الاثنين\",\r\n+\"Tue\":\"الثلاثاء\",\r\n+\"Wed\":\"الاربعاء\",\r\n+\"Thur\":\"الخميس\",\r\n+\"Fri\":\"الجمعة\",\r\n+\"Sat\":\"السبت\",\r\n+\"Sun\":\"الاحد\",\r\n+\"Jan\":\"يناير\",\r\n+\"Feb\":\"فبراير\",\r\n+\"Mar\":\"مارس\",\r\n+\"Apr\":\"ابريل\",\r\n+\"May\":\"مايو\",\r\n+\"June\":\"يونيو \",\r\n+\"Jul\":\"يوليو \",\r\n+\"Aug\":\"أغسطس \",\r\n+\"Sep\":\"سبتمبر \",\r\n+\"Oct\":\"أكتوبر \",\r\n+\"Nov\":\"نوفمبر \",\r\n+\"Dec\":\"ديسمبر \",\r\n+\"Please enter your name\":\"ادخل اسمك رجاء\",\r\n+\"Enter your name\":\"ادخل اسمك\",\r\n+\"Please enter email or username\":\"ادخل البريدالالكتروني رجاء\",\r\n+\"Enter email or username\":\"ادخل البريد الالكتروني\",\r\n+\"Please enter a password\":\"ادخل كلمة المرور رجاء\",\r\n+\"Password\":\"كلمة المرور\",\r\n+\"Please confirm your password\":\"قم باعادة كتابة كلمة المرور رجاء \",\r\n+\"Passwords do not match\":\"كلمات المرور غير متشابهة\",\r\n+\"Confirm Password\":\"التحقق من كلمة المرور\",\r\n+\"----------- OR -----------\":\"----------- أو -----------\",\r\n+\"Entry is restricted\":\"الدخول مقيد\",\r\n+\"Please check with the admin to obtain access permission\":\"الرجاء مراجعة الادمن للحصول على صلاحية الدخول \",\r\n+\"OK\":\"حسنا\",\r\n+\"No data available.\":\"لا يوجد بيانات متاحة.\",\r\n+\"Change User Rloe\":\"تغير دور المستخدم\",\r\n+\"Delete User\":\"حذف المستخدم\",\r\n+\"user information\":\"معلومات المستخدم\",\r\n+\"Name :  \":\"الاسم :  \",\r\n+\"Email :  \":\"ايميل :  \",\r\n+\"Role :  \":\"الدور :  \",\r\n+\"Attention: You are about to change the role of this user\":\"انتبه : انت على وشك ان تغير دور هذا المستخدم\",\r\n+\"Attention: You are about to delete of this user\":\"انتبه : انت على وشك حذف هذا المسخدم\",\r\n+\"The role was changed successfully\":\"تم تغير الدور بنجاح\",\r\n+\"The user was deleted successfully\":\"تم حذف المستخدم بنجاح\",\r\n+\"Confirm\":\"تأكيد\",\r\n+\"admin\":\"ادمن\",\r\n+\"guest\":\"زائر\",\r\n+\"user\":\"مستخدم\",\r\n+\"editor\":\"محرر\"\r\n+\r\n+  }\r\n+\r\n+\r\n"
                },
                {
                    "date": 1695393877808,
                    "content": "Index: \n===================================================================\n--- \n+++ \n@@ -90,9 +90,9 @@\n \"Entry is restricted\":\"الدخول مقيد\",\r\n \"Please check with the admin to obtain access permission\":\"الرجاء مراجعة الادمن للحصول على صلاحية الدخول \",\r\n \"OK\":\"حسنا\",\r\n \"No data available.\":\"لا يوجد بيانات متاحة.\",\r\n-\"Change User Rloe\":\"تغير دور المستخدم\",\r\n+\"Change User Rloe\":\"تغيير دور المستخدم\",\r\n \"Delete User\":\"حذف المستخدم\",\r\n \"user information\":\"معلومات المستخدم\",\r\n \"Name :  \":\"الاسم :  \",\r\n \"Email :  \":\"ايميل :  \",\r\n@@ -109,116 +109,4 @@\n \r\n   }\r\n \r\n \r\n-{\r\n-\"Inbox\":\"الوارد\",\r\n-\"Pending\" :\"معلقة\",\r\n-\"In Progress\":\"جاري المعالجة\",\r\n-\"Completed\":\"مكتمل\",\r\n-\"New Inbox\":\" بريد جديد \",\r\n-\"Home Page\":\" الصفحة الرئيسية\",\r\n-\"Profile Page\" :\"الصفحة الشخصية\",\r\n-\"Senders\" :\"المرسلين\",\r\n-\"User Management\":\"إدارةالمستخدم\",\r\n-\"Terms Of Service\":\"شروط الخدمة\",\r\n-\"Usage Policy\":\"سياسة الاستخدام\",\r\n-\"Search\":\"بحث\",\r\n-\"Login\":\"تسجيل الدخول\",\r\n-\"Sign up\":\"انشاء حساب\",\r\n-\"Foreign\":\"مؤسسات اجنبية\",\r\n-  \"Official Organiztions\":\"مؤسسات حكومية \",\r\n-  \"Official Organizations\":\"مؤسسات حكومية \",\r\n-  \"NGOs\":\"مؤسسات مجتمع المدني \",\r\n-  \"Others\":\"غيرها\",\r\n-  \"Other\":\"غيرها\",\r\n-  \"Tags\":\"علامات\",\r\n-  \"Language\":\"اللغة\",\r\n-  \"Logout\":\"تسجيل الخروج\",\r\n-  \"Edit Profile\":\"تعديل الملف الشخصي \",\r\n-  \"Name:\":\"الاسم:\",\r\n-  \"UPDATE PROFILE\":\"تحديث  الملف الشخصي\",\r\n-  \"Email:\":\"ايميل:\",\r\n-  \"Role:\":\"الدور:\",\r\n-  \"Cancel\":\"الغاء\",\r\n-  \"Filter\":\"فلترة\",\r\n-  \"Done\":\"تاكيد\",\r\n-  \"Clear\":\"مسح الاختيار\",\r\n-  \"Start Date\":\"تاريخ البدء\",\r\n-  \"End Date\":\"تاريخ الانتهاء\",\r\n-  \"Sellect Your Date\":\"اختار التاريخ المناسب\",\r\n-  \"Search ...\":\"بحث ...\",\r\n-  \"All Tags\":\"كل العلامات\",\r\n-  \"Sender\":\"المرسل\",\r\n-  \"Please enter a sender name\":\"ادخل اسم المرسل رجاء\",\r\n-  \"Mail Created Successfully\":\"تم انشائ الايميل بنجاح\",\r\n-  \"Please enter a mobile number\":\"ادخل رقم الهاتف رجاء\",\r\n-  \"Mobile\":\"الهاتف\",\r\n-  \"Category\":\"الفئة\",\r\n-  \"Please enter a title of mail\":\"ادخل عنوان الايميل رجاء\",\r\n-  \"Title of mail\":\"عنوان الايميل\",\r\n-  \"Description\":\"الوصف\",\r\n-  \"Please enter an archive number\":\"ادخل رقم الارشيف رجاء\",\r\n-  \"Archive number\":\"رقم الارشيف\",\r\n-  \"Add Decsision ...\":\"ادخل القرار ...\",\r\n-  \"Add image\":\"اضف صورة\",\r\n-  \"Descision\":\"القرار\",\r\n-  \"Add new activity ...\":\"اضف نشاط جديد ...\",\r\n-  \"Activity\":\"النشاط\",\r\n-  \"Mail Details\":\"تفاصيل الايميل\",\r\n-\"Mail Updated Successfully\":\"تم تحديث الايميل بنجاح\",\r\n-\"Status\":\"الحالة\",\r\n-\"Add status\":\"اضافة حالة\",\r\n-\"Add new tag ...\":\"اضافة علامة ...\",\r\n-\"Date\":\"التاريخ\",\r\n-\"Mon\":\"الاثنين\",\r\n-\"Tue\":\"الثلاثاء\",\r\n-\"Wed\":\"الاربعاء\",\r\n-\"Thur\":\"الخميس\",\r\n-\"Fri\":\"الجمعة\",\r\n-\"Sat\":\"السبت\",\r\n-\"Sun\":\"الاحد\",\r\n-\"Jan\":\"يناير\",\r\n-\"Feb\":\"فبراير\",\r\n-\"Mar\":\"مارس\",\r\n-\"Apr\":\"ابريل\",\r\n-\"May\":\"مايو\",\r\n-\"June\":\"يونيو \",\r\n-\"Jul\":\"يوليو \",\r\n-\"Aug\":\"أغسطس \",\r\n-\"Sep\":\"سبتمبر \",\r\n-\"Oct\":\"أكتوبر \",\r\n-\"Nov\":\"نوفمبر \",\r\n-\"Dec\":\"ديسمبر \",\r\n-\"Please enter your name\":\"ادخل اسمك رجاء\",\r\n-\"Enter your name\":\"ادخل اسمك\",\r\n-\"Please enter email or username\":\"ادخل البريدالالكتروني رجاء\",\r\n-\"Enter email or username\":\"ادخل البريد الالكتروني\",\r\n-\"Please enter a password\":\"ادخل كلمة المرور رجاء\",\r\n-\"Password\":\"كلمة المرور\",\r\n-\"Please confirm your password\":\"قم باعادة كتابة كلمة المرور رجاء \",\r\n-\"Passwords do not match\":\"كلمات المرور غير متشابهة\",\r\n-\"Confirm Password\":\"التحقق من كلمة المرور\",\r\n-\"----------- OR -----------\":\"----------- أو -----------\",\r\n-\"Entry is restricted\":\"الدخول مقيد\",\r\n-\"Please check with the admin to obtain access permission\":\"الرجاء مراجعة الادمن للحصول يعطيك صلاحية الدخول \",\r\n-\"OK\":\"حسنا\",\r\n-\"No data available.\":\"لا يوجد بيانات متاحة.\",\r\n-\"Change User Rloe\":\"تغير دور المستخدم\",\r\n-\"Delete User\":\"حذف المستخدم\",\r\n-\"user information\":\"معلومات المستخدم\",\r\n-\"Name :  \":\"الاسم :  \",\r\n-\"Email :  \":\"ايميل :  \",\r\n-\"Role :  \":\"الدور :  \",\r\n-\"Attention: You are about to change the role of this user\":\"انتبه : انت على وشك ان تغير دور هذا المستخدم\",\r\n-\"Attention: You are about to delete of this user\":\"انتبه : انت على وشك حذف هذا المسخدم\",\r\n-\"The role was changed successfully\":\"تم تغير الدور بنجاح\",\r\n-\"The user was deleted successfully\":\"تم حذف المستخدم بنجاح\",\r\n-\"Confirm\":\"تأكيد\",\r\n-\"admin\":\"ادمن\",\r\n-\"guest\":\"زائر\",\r\n-\"user\":\"مستخدم\",\r\n-\"editor\":\"محرر\"\r\n-\r\n-  }\r\n-\r\n-\r\n"
                },
                {
                    "date": 1695393893679,
                    "content": "Index: \n===================================================================\n--- \n+++ \n@@ -96,9 +96,9 @@\n \"user information\":\"معلومات المستخدم\",\r\n \"Name :  \":\"الاسم :  \",\r\n \"Email :  \":\"ايميل :  \",\r\n \"Role :  \":\"الدور :  \",\r\n-\"Attention: You are about to change the role of this user\":\"انتبه : انت على وشك ان تغير دور هذا المستخدم\",\r\n+\"Attention: You are about to change the role of this user\":\"انتبه : انت على وشك تغيير دور هذا المستخدم\",\r\n \"Attention: You are about to delete of this user\":\"انتبه : انت على وشك حذف هذا المسخدم\",\r\n \"The role was changed successfully\":\"تم تغير الدور بنجاح\",\r\n \"The user was deleted successfully\":\"تم حذف المستخدم بنجاح\",\r\n \"Confirm\":\"تأكيد\",\r\n"
                },
                {
                    "date": 1695393917212,
                    "content": "Index: \n===================================================================\n--- \n+++ \n@@ -37,9 +37,9 @@\n   \"Search ...\":\"بحث ...\",\r\n   \"All Tags\":\"كل العلامات\",\r\n   \"Sender\":\"المرسل\",\r\n   \"Please enter a sender name\":\"ادخل اسم المرسل رجاء\",\r\n-  \"Mail Created Successfully\":\"تم انشائ الايميل بنجاح\",\r\n+  \"Mail Created Successfully\":\"تم انشا الايميل بنجاح\",\r\n   \"Please enter a mobile number\":\"ادخل رقم الهاتف رجاء\",\r\n   \"Mobile\":\"الهاتف\",\r\n   \"Category\":\"الفئة\",\r\n   \"Please enter a title of mail\":\"ادخل عنوان الايميل رجاء\",\r\n@@ -98,9 +98,9 @@\n \"Email :  \":\"ايميل :  \",\r\n \"Role :  \":\"الدور :  \",\r\n \"Attention: You are about to change the role of this user\":\"انتبه : انت على وشك تغيير دور هذا المستخدم\",\r\n \"Attention: You are about to delete of this user\":\"انتبه : انت على وشك حذف هذا المسخدم\",\r\n-\"The role was changed successfully\":\"تم تغير الدور بنجاح\",\r\n+\"The role was changed successfully\":\"تم تغيير الدور بنجاح\",\r\n \"The user was deleted successfully\":\"تم حذف المستخدم بنجاح\",\r\n \"Confirm\":\"تأكيد\",\r\n \"admin\":\"ادمن\",\r\n \"guest\":\"زائر\",\r\n"
                },
                {
                    "date": 1695393927032,
                    "content": "Index: \n===================================================================\n--- \n+++ \n@@ -37,9 +37,9 @@\n   \"Search ...\":\"بحث ...\",\r\n   \"All Tags\":\"كل العلامات\",\r\n   \"Sender\":\"المرسل\",\r\n   \"Please enter a sender name\":\"ادخل اسم المرسل رجاء\",\r\n-  \"Mail Created Successfully\":\"تم انشا الايميل بنجاح\",\r\n+  \"Mail Created Successfully\":\"تم انشاء الايميل بنجاح\",\r\n   \"Please enter a mobile number\":\"ادخل رقم الهاتف رجاء\",\r\n   \"Mobile\":\"الهاتف\",\r\n   \"Category\":\"الفئة\",\r\n   \"Please enter a title of mail\":\"ادخل عنوان الايميل رجاء\",\r\n"
                }
            ],
            "date": 1695393771288,
            "name": "Commit-0",
            "content": "{\r\n\"Inbox\":\"الوارد\",\r\n\"Pending\" :\"معلقة\",\r\n\"In Progress\":\"جاري المعالجة\",\r\n\"Completed\":\"مكتمل\",\r\n\"New Inbox\":\" بريد جديد \",\r\n\"Home Page\":\" الصفحة الرئيسية\",\r\n\"Profile Page\" :\"الصفحة الشخصية\",\r\n\"Senders\" :\"المرسلين\",\r\n\"User Management\":\"إدارةالمستخدم\",\r\n\"Terms Of Service\":\"شروط الخدمة\",\r\n\"Usage Policy\":\"سياسة الاستخدام\",\r\n\"Search\":\"بحث\",\r\n\"Login\":\"تسجيل الدخول\",\r\n\"Sign up\":\"انشاء حساب\",\r\n\"Foreign\":\"مؤسسات اجنبية\",\r\n  \"Official Organiztions\":\"مؤسسات حكومية \",\r\n  \"Official Organizations\":\"مؤسسات حكومية \",\r\n  \"NGOs\":\"مؤسسات مجتمع المدني \",\r\n  \"Others\":\"غيرها\",\r\n  \"Other\":\"غيرها\",\r\n  \"Tags\":\"علامات\",\r\n  \"Language\":\"اللغة\",\r\n  \"Logout\":\"تسجيل الخروج\",\r\n  \"Edit Profile\":\"تعديل الملف الشخصي \",\r\n  \"Name:\":\"الاسم:\",\r\n  \"UPDATE PROFILE\":\"تحديث  الملف الشخصي\",\r\n  \"Email:\":\"ايميل:\",\r\n  \"Role:\":\"الدور:\",\r\n  \"Cancel\":\"الغاء\",\r\n  \"Filter\":\"فلترة\",\r\n  \"Done\":\"تاكيد\",\r\n  \"Clear\":\"مسح الاختيار\",\r\n  \"Start Date\":\"تاريخ البدء\",\r\n  \"End Date\":\"تاريخ الانتهاء\",\r\n  \"Sellect Your Date\":\"اختار التاريخ المناسب\",\r\n  \"Search ...\":\"بحث ...\",\r\n  \"All Tags\":\"كل العلامات\",\r\n  \"Sender\":\"المرسل\",\r\n  \"Please enter a sender name\":\"ادخل اسم المرسل رجاء\",\r\n  \"Mail Created Successfully\":\"تم انشائ الايميل بنجاح\",\r\n  \"Please enter a mobile number\":\"ادخل رقم الهاتف رجاء\",\r\n  \"Mobile\":\"الهاتف\",\r\n  \"Category\":\"الفئة\",\r\n  \"Please enter a title of mail\":\"ادخل عنوان الايميل رجاء\",\r\n  \"Title of mail\":\"عنوان الايميل\",\r\n  \"Description\":\"الوصف\",\r\n  \"Please enter an archive number\":\"ادخل رقم الارشيف رجاء\",\r\n  \"Archive number\":\"رقم الارشيف\",\r\n  \"Add Decsision ...\":\"ادخل القرار ...\",\r\n  \"Add image\":\"اضف صورة\",\r\n  \"Descision\":\"القرار\",\r\n  \"Add new activity ...\":\"اضف نشاط جديد ...\",\r\n  \"Activity\":\"النشاط\",\r\n  \"Mail Details\":\"تفاصيل الايميل\",\r\n\"Mail Updated Successfully\":\"تم تحديث الايميل بنجاح\",\r\n\"Status\":\"الحالة\",\r\n\"Add status\":\"اضافة حالة\",\r\n\"Add new tag ...\":\"اضافة علامة ...\",\r\n\"Date\":\"التاريخ\",\r\n\"Mon\":\"الاثنين\",\r\n\"Tue\":\"الثلاثاء\",\r\n\"Wed\":\"الاربعاء\",\r\n\"Thur\":\"الخميس\",\r\n\"Fri\":\"الجمعة\",\r\n\"Sat\":\"السبت\",\r\n\"Sun\":\"الاحد\",\r\n\"Jan\":\"يناير\",\r\n\"Feb\":\"فبراير\",\r\n\"Mar\":\"مارس\",\r\n\"Apr\":\"ابريل\",\r\n\"May\":\"مايو\",\r\n\"June\":\"يونيو \",\r\n\"Jul\":\"يوليو \",\r\n\"Aug\":\"أغسطس \",\r\n\"Sep\":\"سبتمبر \",\r\n\"Oct\":\"أكتوبر \",\r\n\"Nov\":\"نوفمبر \",\r\n\"Dec\":\"ديسمبر \",\r\n\"Please enter your name\":\"ادخل اسمك رجاء\",\r\n\"Enter your name\":\"ادخل اسمك\",\r\n\"Please enter email or username\":\"ادخل البريدالاكتروني رجاء\",\r\n\"Enter email or username\":\"ادخل البريد الاكتروني\",\r\n\"Please enter a password\":\"ادخل كلمة السر رجاء\",\r\n\"Password\":\"كلمة المرور\",\r\n\"Please confirm your password\":\"قم باعادة كتابة كلمة السر رجاء \",\r\n\"Passwords do not match\":\"كلمات السر غير متشابهة\",\r\n\"Confirm Password\":\"التحقق من كلمة السر\",\r\n\"----------- OR -----------\":\"----------- او -----------\",\r\n\"Entry is restricted\":\"الدخول مقيد\",\r\n\"Please check with the admin to obtain access permission\":\"الرجاء مراجعة الادمن حتى يعطيك صلاحية الدخول \",\r\n\"OK\":\"حسنا\",\r\n\"No data available.\":\"لا يوجد بيانات متاحة.\",\r\n\"Change User Rloe\":\"تغير دور المستخدم\",\r\n\"Delete User\":\"حذف المستخدم\",\r\n\"user information\":\"معلومات المستخدم\",\r\n\"Name :  \":\"الاسم :  \",\r\n\"Email :  \":\"ايميل :  \",\r\n\"Role :  \":\"الدور :  \",\r\n\"Attention: You are about to change the role of this user\":\"انتبه : انت على وشك ان تغير دور هذا المستخدم\",\r\n\"Attention: You are about to delete of this user\":\"انتبه : انت على وشك حذف هذا المسخدم\",\r\n\"The role was changed successfully\":\"تم تغير الدور بنجاح\",\r\n\"The user was deleted successfully\":\"تم حذف المستخدم بنجاح\",\r\n\"Confirm\":\"تأكيد\",\r\n\"admin\":\"ادمن\",\r\n\"guest\":\"زائر\",\r\n\"user\":\"مستخدم\",\r\n\"editor\":\"محرر\"\r\n\r\n  }\r\n\r\n\r\n"
        }
    ]
}